dochain_block/__init__.py
dochain_block/__version__.py
dochain_block/lc_openai.py
dochain_block/nacos.py
dochain_block/nacos_prompt.py
dochain_block/openapi_block.py
dochain_block/ai/__init__.py
dochain_block/ai/prompt_block.py
dochain_block-0.3.2.dist-info/METADATA
dochain_block-0.3.2.dist-info/WHEEL
dochain_block-0.3.2.dist-info/RECORD
