Metadata-Version: 2.4
Name: dochain-block
Version: 0.3.2
Summary: Prefect Blocks for authentication and connection management
Author-email: Your Name <your.email@example.com>
License: MIT
Keywords: authentication,blocks,connection-management,nacos,prefect
Classifier: Development Status :: 4 - Beta
Classifier: Intended Audience :: Developers
Classifier: License :: OSI Approved :: MIT License
Classifier: Programming Language :: Python :: 3
Classifier: Programming Language :: Python :: 3.11
Classifier: Programming Language :: Python :: 3.12
Requires-Python: >=3.11
Requires-Dist: httpx>=0.28.1
Requires-Dist: langchain-openai>=1.0.1
Requires-Dist: nacos-sdk-python>=2.0.9
Requires-Dist: prefect>=3.4.24
Requires-Dist: pydantic>=2.12.3
